pyopenapi/__init__.py
pyopenapi/__main__.py
pyopenapi/decorators.py
pyopenapi/generator.py
pyopenapi/metadata.py
pyopenapi/operations.py
pyopenapi/options.py
pyopenapi/proxy.py
pyopenapi/py.typed
pyopenapi/specification.py
pyopenapi/template.html
pyopenapi/utility.py
python_openapi-0.2.0.dist-info/licenses/LICENSE
python_openapi-0.2.0.dist-info/METADATA
python_openapi-0.2.0.dist-info/WHEEL
python_openapi-0.2.0.dist-info/top_level.txt
python_openapi-0.2.0.dist-info/zip-safe
python_openapi-0.2.0.dist-info/RECORD
